[
{
    "model": "catalog.category",
    "pk": 1,
    "fields": {
        "name": "Смартфоны",
        "description": "Смартфоны, как средство не только коммуникации, но и получения дополнительных функций для удобства жизни"
    }
},
{
    "model": "catalog.category",
    "pk": 2,
    "fields": {
        "name": "Телевизоры",
        "description": "Современный телевизор, который позволяет наслаждаться просмотром, станет вашим другом и помощником"
    }
},
{
    "model": "catalog.category",
    "pk": 3,
    "fields": {
        "name": "Холодильники",
        "description": "Холодильники - восьмое чудо света"
    }
}
]
